threedi_raster_edits/__init__.py
threedi_raster_edits/requirements.txt
threedi_raster_edits/examples/__init__.py
threedi_raster_edits/examples/dem_sampling.py
threedi_raster_edits/examples/dem_sampling_linestrings.py
threedi_raster_edits/examples/extract_raster_data_using_geometries.py
threedi_raster_edits/examples/merge_vector_files.py
threedi_raster_edits/examples/merging_linestrings_based_on_heights.py
threedi_raster_edits/examples/profielen_overijssels_kanaal_to_threedi.py
threedi_raster_edits/examples/sideview.py
threedi_raster_edits/examples/threedi_model_edits.py
threedi_raster_edits/examples/threedi_raster_extraction.py
threedi_raster_edits/examples/vonoroi_polygons_from_linestrings.py
threedi_raster_edits/gis/__init__.py
threedi_raster_edits/gis/feature.py
threedi_raster_edits/gis/fields.py
threedi_raster_edits/gis/geometries.py
threedi_raster_edits/gis/geometry.py
threedi_raster_edits/gis/geotransform.py
threedi_raster_edits/gis/linestring.py
threedi_raster_edits/gis/point.py
threedi_raster_edits/gis/polygon.py
threedi_raster_edits/gis/raster.py
threedi_raster_edits/gis/rastergroup.py
threedi_raster_edits/gis/spatial_reference.py
threedi_raster_edits/gis/utils.py
threedi_raster_edits/gis/vector.py
threedi_raster_edits/gis/vectorgroup.py
threedi_raster_edits/lizard/__init__.py
threedi_raster_edits/lizard/rextract.py
threedi_raster_edits/lizard/uuid.py
threedi_raster_edits/tests/__init__.py
threedi_raster_edits/tests/benchmark.json
threedi_raster_edits/tests/test_gis_feature.py
threedi_raster_edits/tests/test_gis_geometry.py
threedi_raster_edits/tests/test_gis_linestring.py
threedi_raster_edits/tests/test_gis_raster.py
threedi_raster_edits/tests/test_gis_rastergroup.py
threedi_raster_edits/tests/test_gis_vector.py
threedi_raster_edits/tests/test_gis_vector.py.bak
threedi_raster_edits/tests/test_lizard_rextract.py
threedi_raster_edits/tests/test_threedi_edits.py
threedi_raster_edits/tests/test_threedi_rastergroup.py
threedi_raster_edits-0.27.dist-info/LICENSE
threedi_raster_edits-0.27.dist-info/METADATA
threedi_raster_edits-0.27.dist-info/WHEEL
threedi_raster_edits-0.27.dist-info/entry_points.txt
threedi_raster_edits-0.27.dist-info/top_level.txt
threedi_raster_edits-0.27.dist-info/RECORD
