Metadata-Version: 2.1
Name: threedi-raster-edits
Version: 0.27
Summary: Threedi Raster Edits provides python tooling for threedi such as raster-conversion, alignment, fillers, checks and others
Home-page: https://github.com/nens/threedi-raster-edits
Author: Chris Kerklaan
Author-email: chris.kerklaan@nelen-schuurmans.nl
License: MIT
Platform: UNKNOWN
Classifier: Programming Language :: Python
Classifier: Framework :: Django
Requires-Dist: cached-property
Requires-Dist: rtree
Requires-Dist: scipy
Provides-Extra: test
Requires-Dist: mock ; extra == 'test'
Requires-Dist: pytest ; extra == 'test'
Requires-Dist: pytest-benchmark ; extra == 'test'
Requires-Dist: pytest-black ; extra == 'test'
Requires-Dist: pytest-cov ; extra == 'test'
Requires-Dist: pytest-flakes ; extra == 'test'
